Metadata-Version: 1.0
Name: mail-auth-utils
Version: 1.0
Summary: Mail auth utilities
Home-page: https://github.com/eklitzke/mail-auth-utils/
Author: Evan Klitzke
Author-email: evan@eklitzke.org
License: GPLv3+
Platform: UNKNOWN
